{"name":"Regex-crossword","tagline":"Implementation of a RegExp crossword.","body":"regex-crossword\r\n===============\r\n\r\nImplementation of a RegExp crossword.\r\n\r\nView the current version at http://jimbly.github.com/regex-crossword/\r\n\r\nOriginal puzzle from http://www.i-programmer.info/news/144-graphics-and-games/5450-can-you-do-the-regular-expression-crossword.html\r\n\r\nTODO List\r\n=========\r\n* Auto-check against known solution\r\n* Allow choosing between multiple crosswords puzzles\r\n* Allow users to save their own puzzles and load other people's\r\n* Track time spent solving puzzle\r\n* Rotate buttons\r\n* Undo/redo\r\n\r\n","google":"","note":"Don't delete this file! It's used internally to help with page regeneration."}